sphinx_builder_classes/__init__.py
sphinx_builder_classes/_version.py
sphinx_builder_classes/_version.pyi
sphinx_builder_classes/py.typed
sphinx_builder_classes-0.1.0.dist-info/METADATA
sphinx_builder_classes-0.1.0.dist-info/WHEEL
sphinx_builder_classes-0.1.0.dist-info/licenses/LICENSE
sphinx_builder_classes-0.1.0.dist-info/RECORD
